confluence/constants.py
confluence/main.py
confluence/models/__init__.py
confluence/models/base.py
confluence/models/common.py
confluence/models/page.py
confluence/models/search.py
confluence/models/space.py
confluence/search.py
confluence/utility/__init__.py
confluence/utility/extract_confluence_page_ids.py
confluence/utility/extract_plantuml.py
confluence/utility/parse_confluence_url.py
confluence/utils.py
service/__init__.py
service/main.py
service/mcp_service.py
confluence_mcp_tool-0.3.0.dist-info/METADATA
confluence_mcp_tool-0.3.0.dist-info/WHEEL
confluence_mcp_tool-0.3.0.dist-info/entry_points.txt
confluence_mcp_tool-0.3.0.dist-info/RECORD
