Metadata-Version: 2.3
Name: confluence-mcp-tool
Version: 0.3.0
Summary: 
Author: Michael Tan
Author-email: michael.tan@scbtechx.io
Requires-Python: >=3.11,<4.0
Classifier: Programming Language :: Python :: 3
Classifier: Programming Language :: Python :: 3.11
Classifier: Programming Language :: Python :: 3.12
Classifier: Programming Language :: Python :: 3.13
Requires-Dist: atlassian-python-api (>=4.0.4,<5.0.0)
Requires-Dist: fastapi (>=0.115.12,<0.116.0)
Requires-Dist: fastmcp (>=2.8.1,<3.0.0)
Requires-Dist: python-dotenv (>=1.1.0,<2.0.0)
Requires-Dist: uvicorn (>=0.34.2,<0.35.0)
